colosseumrl/BaseEnvironment.py
colosseumrl/ClientEnvironment.py
colosseumrl/FrameRateKeeper.py
colosseumrl/RLApp.py
colosseumrl/__init__.py
colosseumrl/config.py
colosseumrl/data_model.py
colosseumrl/match_server.py
colosseumrl/matchmaking_server.py
colosseumrl/rl_logging.py
colosseumrl/util.py
colosseumrl/envs/__init__.py
colosseumrl/envs/blokus/BlokusClientEnvironment.py
colosseumrl/envs/blokus/BlokusEnvironment.py
colosseumrl/envs/blokus/__init__.py
colosseumrl/envs/blokus/ai.py
colosseumrl/envs/blokus/board.py
colosseumrl/envs/blokus/computation.py
colosseumrl/envs/blokus/gui.py
colosseumrl/envs/blokus/main.py
colosseumrl/envs/testgame/TestGame.py
colosseumrl/envs/testgame/__init__.py
colosseumrl/envs/tictactoe/__init__.py
colosseumrl/envs/tictactoe/tictactoe_2p_env.py
colosseumrl/envs/tictactoe/tictactoe_3p_env.py
colosseumrl/envs/tictactoe/tictactoe_4p_env.py
colosseumrl/envs/tron/CyTronGrid.cpython-37m-darwin.so
colosseumrl/envs/tron/TronGridClientEnvironment.py
colosseumrl/envs/tron/TronGridEnvironment.py
colosseumrl/envs/tron/__init__.py
colosseumrl/envs/tron/compile.py
colosseumrl/examples/__init__.py
colosseumrl/examples/blokus_client.py
colosseumrl/examples/blokus_multi_client.py
colosseumrl/examples/human_tron_client.py
colosseumrl/examples/tron_client.py
colosseumrl/matchmaking/MatchmakingClient.py
colosseumrl/matchmaking/MatchmakingServer.py
colosseumrl/matchmaking/RankingDatabase.py
colosseumrl/matchmaking/__init__.py
colosseumrl/matchmaking/grpc_gen/__init__.py
colosseumrl/matchmaking/grpc_gen/server_pb2.py
colosseumrl/matchmaking/grpc_gen/server_pb2_grpc.py
colosseumrl-1.0.4.dist-info/LICENSE
colosseumrl-1.0.4.dist-info/METADATA
colosseumrl-1.0.4.dist-info/WHEEL
colosseumrl-1.0.4.dist-info/top_level.txt
colosseumrl-1.0.4.dist-info/RECORD
