Metadata-Version: 2.1
Name: colosseumrl
Version: 1.0.4
Summary: UC Irvine multi-agent reinforcement learning framework
Home-page: https://github.com/colosseumrl/Colosseum
Author: Alexander Shmakov
Author-email: alexanders101@gmail.com
License: UNKNOWN
Platform: UNKNOWN
Classifier: Programming Language :: Python :: 3.5
Classifier: Programming Language :: Python :: 3.6
Classifier: Programming Language :: Python :: 3.7
Classifier: License :: OSI Approved :: MIT License
Classifier: Operating System :: OS Independent
Requires-Dist: wheel
Requires-Dist: setuptools
Requires-Dist: scipy
Requires-Dist: grpcio
Requires-Dist: grpcio-tools
Requires-Dist: Cython
Requires-Dist: pygame
Requires-Dist: numba
Requires-Dist: numpy
Requires-Dist: dill
Requires-Dist: zmq
Requires-Dist: trueskill
Requires-Dist: spacetime
